bx/__init__.py
bx/_seqmapping.cpython-314-aarch64-linux-gnu.so
bx/binned_array.py
bx/binned_array_tests.py
bx/bitset.cpython-314-aarch64-linux-gnu.so
bx/bitset_builders.py
bx/bitset_tests.py
bx/bitset_utils.py
bx/filter.py
bx/gene_reader.py
bx/interval_index_file.py
bx/interval_index_file_tests.py
bx/seqmapping.py
bx/seqmapping_tests.py
bx/wiggle.py
bx/wiggle_tests.py
bx/align/__init__.py
bx/align/_core.cpython-314-aarch64-linux-gnu.so
bx/align/_epo.cpython-314-aarch64-linux-gnu.so
bx/align/axt.py
bx/align/core.py
bx/align/epo.py
bx/align/epo_tests.py
bx/align/lav.py
bx/align/lav_tests.py
bx/align/maf.py
bx/align/maf_tests.py
bx/align/score.py
bx/align/score_tests.py
bx/align/sitemask/__init__.py
bx/align/sitemask/_cpg.cpython-314-aarch64-linux-gnu.so
bx/align/sitemask/core.py
bx/align/sitemask/cpg.py
bx/align/sitemask/quality.py
bx/align/sitemask/sitemask_tests.py
bx/align/tools/__init__.py
bx/align/tools/chop.py
bx/align/tools/fuse.py
bx/align/tools/thread.py
bx/align/tools/tile.py
bx/arrays/__init__.py
bx/arrays/array_tree.cpython-314-aarch64-linux-gnu.so
bx/arrays/array_tree_tests.py
bx/arrays/bed.cpython-314-aarch64-linux-gnu.so
bx/arrays/wiggle.cpython-314-aarch64-linux-gnu.so
bx/bbi/__init__.py
bx/bbi/bbi_file.cpython-314-aarch64-linux-gnu.so
bx/bbi/bigbed_file.cpython-314-aarch64-linux-gnu.so
bx/bbi/bigwig_file.cpython-314-aarch64-linux-gnu.so
bx/bbi/bigwig_tests.py
bx/bbi/bpt_file.cpython-314-aarch64-linux-gnu.so
bx/bbi/cirtree_file.cpython-314-aarch64-linux-gnu.so
bx/cookbook/__init__.py
bx/cookbook/attribute.py
bx/cookbook/doc_optparse.py
bx/intervals/__init__.py
bx/intervals/cluster.cpython-314-aarch64-linux-gnu.so
bx/intervals/cluster_tests.py
bx/intervals/intersection.cpython-314-aarch64-linux-gnu.so
bx/intervals/intersection_tests.py
bx/intervals/io.py
bx/intervals/random_intervals.py
bx/intervals/operations/__init__.py
bx/intervals/operations/base_coverage.py
bx_python-0.14.0.dist-info/METADATA
bx_python-0.14.0.dist-info/WHEEL
bx_python-0.14.0.dist-info/top_level.txt
bx_python-0.14.0.dist-info/RECORD
bx_python-0.14.0.dist-info/licenses/LICENSE
