Metadata-Version: 2.4
Name: bx-python
Version: 0.14.0
Summary: Tools for manipulating biological data, particularly multiple sequence alignments
Author: Bob Harris, David King, Brent Pedersen, Kanwei Li
Author-email: James Taylor <james@jamestaylor.org>, Nicola Soranzo <nicola.soranzo@earlham.ac.uk>
License: MIT
Project-URL: Homepage, https://github.com/bxlab/bx-python
Project-URL: Bug Tracker, https://github.com/bxlab/bx-python/issues
Project-URL: Source Code, https://github.com/bxlab/bx-python
Classifier: Development Status :: 5 - Production/Stable
Classifier: Intended Audience :: Developers
Classifier: Intended Audience :: Science/Research
Classifier: Operating System :: POSIX
Classifier: Programming Language :: Python :: 3
Classifier: Programming Language :: Python :: 3.9
Classifier: Programming Language :: Python :: 3.10
Classifier: Programming Language :: Python :: 3.11
Classifier: Programming Language :: Python :: 3.12
Classifier: Programming Language :: Python :: 3.13
Classifier: Programming Language :: Python :: 3.14
Classifier: Topic :: Scientific/Engineering :: Bio-Informatics
Classifier: Topic :: Software Development :: Libraries :: Python Modules
Requires-Python: >=3.9
License-File: LICENSE
Requires-Dist: numpy
Requires-Dist: pyparsing
Dynamic: license-file
